mail2beyond/__init__.py
mail2beyond/framework.py
mail2beyond/tools.py
mail2beyond/connectors/__init__.py
mail2beyond/connectors/discord.py
mail2beyond/connectors/google_chat.py
mail2beyond/connectors/microsoft_teams.py
mail2beyond/connectors/slack.py
mail2beyond/connectors/smtp.py
mail2beyond/connectors/void.py
mail2beyond/parsers/__init__.py
mail2beyond/parsers/auto.py
mail2beyond/parsers/html.py
mail2beyond/parsers/plain.py
mail2beyond-1.0.3.data/scripts/mail2beyond
mail2beyond-1.0.3.dist-info/LICENSE
mail2beyond-1.0.3.dist-info/METADATA
mail2beyond-1.0.3.dist-info/WHEEL
mail2beyond-1.0.3.dist-info/top_level.txt
mail2beyond-1.0.3.dist-info/RECORD
