Metadata-Version: 2.1
Name: mail2beyond
Version: 1.0.3
Summary: A Python based SMTP server package and CLI that redirects incoming SMTP messages to upstream APIs like Google Chat, Slack and more!.
Home-page: https://github.com/soluna-studios/mail2beyond
Author: Jared Hendrickson
Author-email: jaredhendrickson13@gmail.com
License: MIT
Classifier: Programming Language :: Python :: 3
Classifier: License :: OSI Approved :: MIT License
Classifier: Operating System :: OS Independent
Requires-Python: >=3.8
License-File: LICENSE
Requires-Dist: setuptools ~=69.1.1
Requires-Dist: requests ~=2.31.0
Requires-Dist: aiosmtpd ~=1.4.5
Requires-Dist: pyyaml ~=6.0
Requires-Dist: pyOpenSSL ~=24.0.0
Requires-Dist: pylint ~=2.14.5
Requires-Dist: html2text ~=2024.2.26
Requires-Dist: pdoc3 ~=0.10.0
